SpatialDE/__init__.py
SpatialDE/aeh.py
SpatialDE/aha.py
SpatialDE/anndata.py
SpatialDE/base.py
SpatialDE/plot.py
SpatialDE/util.py
SpatialDE/scripts/__init__.py
SpatialDE/scripts/spatialde_cli.py
SpatialDE_SO-1.1.5.1.dist-info/LICENSE
SpatialDE_SO-1.1.5.1.dist-info/METADATA
SpatialDE_SO-1.1.5.1.dist-info/WHEEL
SpatialDE_SO-1.1.5.1.dist-info/entry_points.txt
SpatialDE_SO-1.1.5.1.dist-info/top_level.txt
SpatialDE_SO-1.1.5.1.dist-info/RECORD
